checkdmarc/__init__.py
checkdmarc/_cli.py
checkdmarc/_constants.py
checkdmarc/bimi.py
checkdmarc/dmarc.py
checkdmarc/dnssec.py
checkdmarc/mta_sts.py
checkdmarc/smtp.py
checkdmarc/smtp_tls_reporting.py
checkdmarc/soa.py
checkdmarc/spf.py
checkdmarc/utils.py
checkdmarc/resources/MVACAs.pem
checkdmarc/resources/README.md
checkdmarc/resources/__init__.py
checkdmarc-5.13.3.dist-info/METADATA
checkdmarc-5.13.3.dist-info/WHEEL
checkdmarc-5.13.3.dist-info/entry_points.txt
checkdmarc-5.13.3.dist-info/licenses/LICENSE
checkdmarc-5.13.3.dist-info/RECORD
